AUTHORS.rst
CONTRIBUTING.rst
HISTORY.rst
LICENSE
MANIFEST.in
README.rst
setup.cfg
setup.py
docs/Makefile
docs/authors.rst
docs/conf.py
docs/contributing.rst
docs/history.rst
docs/index.rst
docs/installation.rst
docs/make.bat
docs/readme.rst
docs/usage.rst
etcd3/__init__.py
etcd3/client.py
etcd3/events.py
etcd3/exceptions.py
etcd3/leases.py
etcd3/locks.py
etcd3/members.py
etcd3/transactions.py
etcd3/utils.py
etcd3/watch.py
etcd3/etcdrpc/__init__.py
etcd3/etcdrpc/auth_pb2.py
etcd3/etcdrpc/kv_pb2.py
etcd3/etcdrpc/rpc_pb2.py
etcd3/etcdrpc/rpc_pb2_grpc.py
etcd3_fork.egg-info/PKG-INFO
etcd3_fork.egg-info/SOURCES.txt
etcd3_fork.egg-info/dependency_links.txt
etcd3_fork.egg-info/not-zip-safe
etcd3_fork.egg-info/requires.txt
etcd3_fork.egg-info/top_level.txt
requirements/base.txt
requirements/test.txt
tests/__init__.py
tests/ca.crt
tests/client.crt
tests/client.key
tests/test_etcd3.py