Metadata-Version: 2.1
Name: etcd3-fork
Version: 0.12.1
Summary: Fork of https://github.com/kragniz/python-etcd3
Home-page: https://github.com/dmxlsj/python-etcd3
Author: Sungmin Lee
Author-email: sungmin.cs@gmail.com
License: Apache Software License 2.0
Keywords: etcd3
Platform: UNKNOWN
Classifier: Development Status :: 2 - Pre-Alpha
Classifier: Intended Audience :: Developers
Classifier: License :: OSI Approved :: Apache Software License
Classifier: Natural Language :: English
Classifier: Programming Language :: Python :: 2
Classifier: Programming Language :: Python :: 2.7
Classifier: Programming Language :: Python :: 3
Classifier: Programming Language :: Python :: 3.4
Classifier: Programming Language :: Python :: 3.5
Classifier: Programming Language :: Python :: 3.6
License-File: LICENSE
License-File: AUTHORS.rst
